nishant_outlier_removal_76/__init__.py
nishant_outlier_removal_76/nishant_outlier_removal_76.py
nishant_outlier_removal_76-0.0.2.dist-info/LICENSE
nishant_outlier_removal_76-0.0.2.dist-info/METADATA
nishant_outlier_removal_76-0.0.2.dist-info/WHEEL
nishant_outlier_removal_76-0.0.2.dist-info/top_level.txt
nishant_outlier_removal_76-0.0.2.dist-info/RECORD
