Metadata-Version: 2.1
Name: nishant-outlier-removal-76
Version: 0.0.2
Summary: An outlier removal assignment
Home-page: https://github.com/pypa/sampleproject
Author: Nishant Goel
Author-email: ngoel_be17@thapar.edu
License: UNKNOWN
Platform: UNKNOWN
Classifier: Programming Language :: Python :: 3
Classifier: License :: OSI Approved :: MIT License
Classifier: Operating System :: OS Independent
Requires-Python: >=3.6
